README.rst
mcinstall.py
setup.cfg
setup.py
mcinstall.egg-info/PKG-INFO
mcinstall.egg-info/SOURCES.txt
mcinstall.egg-info/dependency_links.txt
mcinstall.egg-info/entry_points.txt
mcinstall.egg-info/top_level.txt